sybil_extras/__init__.py
sybil_extras/languages.py
sybil_extras/py.typed
sybil_extras/spelling_private_dict.txt
sybil_extras/evaluators/__init__.py
sybil_extras/evaluators/block_accumulator.py
sybil_extras/evaluators/code_block_writer.py
sybil_extras/evaluators/multi.py
sybil_extras/evaluators/no_op.py
sybil_extras/evaluators/shell_evaluator.py
sybil_extras/evaluators/spelling_private_dict.txt
sybil_extras/parsers/__init__.py
sybil_extras/parsers/abstract/__init__.py
sybil_extras/parsers/abstract/_grouping_utils.py
sybil_extras/parsers/abstract/attribute_grouped_source.py
sybil_extras/parsers/abstract/group_all.py
sybil_extras/parsers/abstract/grouped_source.py
sybil_extras/parsers/abstract/spelling_private_dict.txt
sybil_extras/parsers/djot/__init__.py
sybil_extras/parsers/djot/codeblock.py
sybil_extras/parsers/djot/custom_directive_skip.py
sybil_extras/parsers/djot/group_all.py
sybil_extras/parsers/djot/grouped_source.py
sybil_extras/parsers/djot/lexers.py
sybil_extras/parsers/markdown/__init__.py
sybil_extras/parsers/markdown/custom_directive_skip.py
sybil_extras/parsers/markdown/group_all.py
sybil_extras/parsers/markdown/grouped_source.py
sybil_extras/parsers/markdown/spelling_private_dict.txt
sybil_extras/parsers/markdown_it/__init__.py
sybil_extras/parsers/markdown_it/_line_offsets.py
sybil_extras/parsers/markdown_it/codeblock.py
sybil_extras/parsers/markdown_it/custom_directive_skip.py
sybil_extras/parsers/markdown_it/group_all.py
sybil_extras/parsers/markdown_it/grouped_source.py
sybil_extras/parsers/markdown_it/lexers.py
sybil_extras/parsers/mdx/__init__.py
sybil_extras/parsers/mdx/attribute_grouped_source.py
sybil_extras/parsers/mdx/codeblock.py
sybil_extras/parsers/mdx/custom_directive_skip.py
sybil_extras/parsers/mdx/group_all.py
sybil_extras/parsers/mdx/grouped_source.py
sybil_extras/parsers/mdx/lexers.py
sybil_extras/parsers/myst/__init__.py
sybil_extras/parsers/myst/custom_directive_skip.py
sybil_extras/parsers/myst/group_all.py
sybil_extras-2026.1.13.dist-info/licenses/LICENSE
sybil_extras-2026.1.13.dist-info/METADATA
sybil_extras-2026.1.13.dist-info/WHEEL
sybil_extras-2026.1.13.dist-info/top_level.txt
sybil_extras-2026.1.13.dist-info/RECORD
